dinf/__init__.py
dinf/__main__.py
dinf/_version.py
dinf/cli.py
dinf/dinf.py
dinf/dinf_model.py
dinf/discriminator.py
dinf/feature_extractor.py
dinf/misc.py
dinf/parameters.py
dinf/plot.py
dinf/py.typed
dinf/store.py
dinf/tabulate.py
dinf/vcf.py
dinf-0.5.0.dist-info/LICENSE
dinf-0.5.0.dist-info/METADATA
dinf-0.5.0.dist-info/WHEEL
dinf-0.5.0.dist-info/entry_points.txt
dinf-0.5.0.dist-info/top_level.txt
dinf-0.5.0.dist-info/RECORD
